RV8803/RV8803.py
RV8803/RV8803driver.py
RV8803/RV8803example.py
RV8803/__init__.py
RV8803-0.0.4.dist-info/LICENSE
RV8803-0.0.4.dist-info/METADATA
RV8803-0.0.4.dist-info/WHEEL
RV8803-0.0.4.dist-info/top_level.txt
RV8803-0.0.4.dist-info/RECORD
