Metadata-Version: 2.1
Name: RV8803
Version: 0.0.4
Summary: A small package for using the RV8803 real time clock via I2C
Home-page: UNKNOWN
Author: Tran Anh Nguyen
Author-email: nguyenta@umich.com
License: UNKNOWN
Platform: UNKNOWN
Classifier: Programming Language :: Python :: 3
Classifier: License :: OSI Approved :: MIT License
Classifier: Operating System :: OS Independent
Requires-Python: >=3.6
